{
    "bucketName": "bucket",
    "authPolicyName": "s3_amplify_1816b5b7",
    "unauthPolicyName": "s3_amplify_1816b5b7",
    "authRoleName": {
        "Ref": "AuthRoleName"
    },
    "unauthRoleName": {
        "Ref": "UnauthRoleName"
    },
    "selectedGuestPermissions": [
        "s3:GetObject",
        "s3:ListBucket"
    ],
    "selectedAuthenticatedPermissions": [
        "s3:DeleteObject"
    ],
    "s3PermissionsAuthenticatedPublic": "s3:DeleteObject",
    "s3PublicPolicy": "Public_policy_b781e666",
    "s3PermissionsAuthenticatedUploads": "DISALLOW",
    "s3UploadsPolicy": "Uploads_policy_b781e666",
    "s3PermissionsAuthenticatedProtected": "s3:DeleteObject",
    "s3ProtectedPolicy": "Protected_policy_b781e666",
    "s3PermissionsAuthenticatedPrivate": "s3:DeleteObject",
    "s3PrivatePolicy": "Private_policy_b781e666",
    "AuthenticatedAllowList": "DISALLOW",
    "s3ReadPolicy": "read_policy_b781e666",
    "s3PermissionsGuestPublic": "DISALLOW",
    "s3PermissionsGuestUploads": "DISALLOW",
    "GuestAllowList": "DISALLOW",
    "triggerFunction": "NONE"
}